signpost/__init__.py
signpost/decorators.py
signpost/properties.py
signpost/py.typed
signpost/utils.py
signpost-0.2.1.dist-info/LICENSE.txt
signpost-0.2.1.dist-info/WHEEL
signpost-0.2.1.dist-info/METADATA
signpost-0.2.1.dist-info/RECORD
