Metadata-Version: 2.1
Name: signpost
Version: 0.2.1
Summary: Simple decorators and functions for type checking pandas DataFrames at runtime
Home-page: https://github.com/ilsedippenaar/signpost
License: GPL-3.0-only
Keywords: pandas,verification,types,annotate
Author: Ilse Dippenaar
Author-email: ilsedipp@gmail.com
Requires-Python: >=3.6.1,<4.0.0
Classifier: Development Status :: 3 - Alpha
Classifier: License :: OSI Approved :: GNU General Public License v3 (GPLv3)
Classifier: Programming Language :: Python :: 3
Classifier: Programming Language :: Python :: 3.7
Classifier: Programming Language :: Python :: 3.8
Classifier: Programming Language :: Python :: 3.9
Classifier: Topic :: Scientific/Engineering
Classifier: Typing :: Typed
Requires-Dist: numpy (>=1.8,<2.0)
Requires-Dist: pandas (>=0.17)
Project-URL: Repository, https://github.com/ilsedippenaar/signpost
